notebookc/__init__.py
notebookc/notebookc.py
manik_notebookc-1.1.3.dist-info/LICENSE
manik_notebookc-1.1.3.dist-info/METADATA
manik_notebookc-1.1.3.dist-info/WHEEL
manik_notebookc-1.1.3.dist-info/top_level.txt
manik_notebookc-1.1.3.dist-info/RECORD
